genro_storage/__init__.py
genro_storage/api_introspection.py
genro_storage/asyncer_wrapper.py
genro_storage/capabilities.py
genro_storage/decorators.py
genro_storage/exceptions.py
genro_storage/manager.py
genro_storage/node.py
genro_storage/py.typed
genro_storage/backends/__init__.py
genro_storage/backends/base.py
genro_storage/backends/base64.py
genro_storage/backends/fsspec.py
genro_storage/backends/local.py
genro_storage/backends/relative.py
genro_storage-0.4.4.dist-info/licenses/LICENSE
genro_storage-0.4.4.dist-info/METADATA
genro_storage-0.4.4.dist-info/WHEEL
genro_storage-0.4.4.dist-info/top_level.txt
genro_storage-0.4.4.dist-info/RECORD
