Metadata-Version: 2.4
Name: genro-storage
Version: 0.4.4
Summary: Unified storage abstraction for Genropy framework
Author-email: Genropy Team <info@genropy.org>
License: MIT
Project-URL: Homepage, https://github.com/genropy/genro-storage
Project-URL: Documentation, https://genro-storage.readthedocs.io
Project-URL: Repository, https://github.com/genropy/genro-storage
Project-URL: Bug Tracker, https://github.com/genropy/genro-storage/issues
Keywords: storage,filesystem,s3,cloud,genropy
Classifier: Development Status :: 4 - Beta
Classifier: Intended Audience :: Developers
Classifier: License :: OSI Approved :: Apache Software License
Classifier: Programming Language :: Python :: 3
Classifier: Programming Language :: Python :: 3.9
Classifier: Programming Language :: Python :: 3.10
Classifier: Programming Language :: Python :: 3.11
Classifier: Programming Language :: Python :: 3.12
Classifier: Topic :: Software Development :: Libraries :: Python Modules
Classifier: Topic :: System :: Filesystems
Requires-Python: >=3.9
License-File: LICENSE
Requires-Dist: fsspec>=2023.1.0
Requires-Dist: PyYAML>=6.0
Provides-Extra: s3
Requires-Dist: s3fs>=2023.1.0; extra == "s3"
Provides-Extra: gcs
Requires-Dist: gcsfs>=2023.1.0; extra == "gcs"
Provides-Extra: azure
Requires-Dist: adlfs>=2023.1.0; extra == "azure"
Provides-Extra: http
Requires-Dist: aiohttp>=3.8.0; extra == "http"
Provides-Extra: smb
Requires-Dist: smbprotocol>=1.10.0; extra == "smb"
Provides-Extra: sftp
Requires-Dist: paramiko>=3.0.0; extra == "sftp"
Provides-Extra: webdav
Requires-Dist: webdav4>=0.9.0; extra == "webdav"
Provides-Extra: libarchive
Requires-Dist: libarchive-c>=5.0; extra == "libarchive"
Provides-Extra: async
Requires-Dist: asyncer>=0.0.2; extra == "async"
Provides-Extra: all
Requires-Dist: s3fs>=2023.1.0; extra == "all"
Requires-Dist: gcsfs>=2023.1.0; extra == "all"
Requires-Dist: adlfs>=2023.1.0; extra == "all"
Requires-Dist: aiohttp>=3.8.0; extra == "all"
Requires-Dist: smbprotocol>=1.10.0; extra == "all"
Requires-Dist: paramiko>=3.0.0; extra == "all"
Requires-Dist: webdav4>=0.9.0; extra == "all"
Requires-Dist: libarchive-c>=5.0; extra == "all"
Requires-Dist: asyncer>=0.0.2; extra == "all"
Provides-Extra: docs
Requires-Dist: sphinx>=7.0; extra == "docs"
Requires-Dist: sphinx-rtd-theme>=2.0; extra == "docs"
Requires-Dist: sphinx-autodoc-typehints>=1.24; extra == "docs"
Requires-Dist: myst-parser>=2.0; extra == "docs"
Provides-Extra: dev
Requires-Dist: pytest>=7.0; extra == "dev"
Requires-Dist: pytest-cov>=4.0; extra == "dev"
Requires-Dist: pytest-asyncio>=0.21.0; extra == "dev"
Requires-Dist: black>=23.0; extra == "dev"
Requires-Dist: ruff>=0.1.0; extra == "dev"
Requires-Dist: mypy>=1.0; extra == "dev"
Requires-Dist: boto3>=1.26.0; extra == "dev"
Requires-Dist: asyncer>=0.0.2; extra == "dev"
Dynamic: license-file
